hycrypt/__about__.py
hycrypt/__init__.py
hycrypt/hycrypt.py
hycrypt/file_cryptosystem/__init__.py
hycrypt/file_cryptosystem/file_cryptosystem.py
hycrypt-1.1.dist-info/licenses/LICENSE
hycrypt-1.1.dist-info/METADATA
hycrypt-1.1.dist-info/WHEEL
hycrypt-1.1.dist-info/top_level.txt
hycrypt-1.1.dist-info/RECORD
