Metadata-Version: 2.4
Name: hycrypt
Version: 1.1
Summary: Stateless-overwrite hybrid cryptosystem for Python
Author-email: Sira Pornsiriprasert <code@psira.me>
License-Expression: BSD-3-Clause
Project-URL: Homepage, https://github.com/p-sira/hycrypt
Project-URL: Documentation, https://p-sira.github.io/hycrypt
Project-URL: Repository, https://github.com/p-sira/hycrypt
Project-URL: Issues, https://github.com/p-sira/hycrypt/issues
Project-URL: Changelog, https://github.com/p-sira/hycrypt/blob/main/CHANGELOG.md
Classifier: Programming Language :: Python :: 3
Classifier: Programming Language :: Python :: 3.10
Classifier: Programming Language :: Python :: 3.11
Classifier: Programming Language :: Python :: 3.12
Classifier: Programming Language :: Python :: 3.13
Classifier: Operating System :: OS Independent
Classifier: Topic :: Security :: Cryptography
Requires-Python: >=3.10
License-File: LICENSE
Requires-Dist: cryptography
Dynamic: license-file
